[
  {
    "name": "Flor d'Ametler Eau de Toilette",
    "brand": "Flor d'Ametler",
    "category": "Eau de Toilette",
    "variants": [
      {
        "id": "",
        "type": "ML",
        "price": "25.65",
        "photos": [
          "https://www.perfumestintin.com/21053564-large_default/flor-d-ametller-flor-d-ametler-eau-de-toilette.jpg",
          "https://www.perfumestintin.com/21053564-cart_default/flor-d-ametller-flor-d-ametler-eau-de-toilette.jpg"
        ],
        "is_active": true,
        "quantity": "50",
        "description": "Genuino perfume de MALLORCA elaborado artesanalmente con métodos tradicionales y de producción limitada.",
        "discount_price": "21.50"
      }
    ]
  }
]